grnkit/__init__.py
grnkit/data.py
grnkit/evaluate.py
grnkit/BoolODE/BoolODE.py
grnkit/BoolODE/LICENSE
grnkit/BoolODE/__init__.py
grnkit/BoolODE/simulator.py
grnkit/BoolODE/utils.py
grnkit/ss/GENIE3.py
grnkit/ss/__init__.py
grnkit/ss/notears.py
grnkit/ts/dynGENIE3.py
grnkit-0.0.3.dist-info/LICENSE
grnkit-0.0.3.dist-info/WHEEL
grnkit-0.0.3.dist-info/METADATA
grnkit-0.0.3.dist-info/RECORD
